odoo/addons/hr_attendance_autoclose/README.rst
odoo/addons/hr_attendance_autoclose/__init__.py
odoo/addons/hr_attendance_autoclose/__manifest__.py
odoo/addons/hr_attendance_autoclose/data/hr_attendance.xml
odoo/addons/hr_attendance_autoclose/data/hr_attendance_reason.xml
odoo/addons/hr_attendance_autoclose/i18n/es.po
odoo/addons/hr_attendance_autoclose/i18n/es_ES.po
odoo/addons/hr_attendance_autoclose/i18n/gl.po
odoo/addons/hr_attendance_autoclose/i18n/hr_attendance_autoclose.pot
odoo/addons/hr_attendance_autoclose/models/__init__.py
odoo/addons/hr_attendance_autoclose/models/hr_attendance.py
odoo/addons/hr_attendance_autoclose/models/hr_employee.py
odoo/addons/hr_attendance_autoclose/models/res_company.py
odoo/addons/hr_attendance_autoclose/readme/CONTRIBUTORS.rst
odoo/addons/hr_attendance_autoclose/readme/DESCRIPTION.rst
odoo/addons/hr_attendance_autoclose/readme/USAGE.rst
odoo/addons/hr_attendance_autoclose/static/description/icon.png
odoo/addons/hr_attendance_autoclose/static/description/index.html
odoo/addons/hr_attendance_autoclose/tests/__init__.py
odoo/addons/hr_attendance_autoclose/tests/test_hr_attendance_auto_close.py
odoo/addons/hr_attendance_autoclose/views/hr_attendance_view.xml
odoo/addons/hr_attendance_autoclose/views/hr_employee.xml
odoo/addons/hr_attendance_autoclose/views/res_company_view.xml
odoo11_addon_hr_attendance_autoclose-11.0.1.3.0.dist-info/METADATA
odoo11_addon_hr_attendance_autoclose-11.0.1.3.0.dist-info/WHEEL
odoo11_addon_hr_attendance_autoclose-11.0.1.3.0.dist-info/top_level.txt
odoo11_addon_hr_attendance_autoclose-11.0.1.3.0.dist-info/RECORD
